{
	"products": [
		{
			"description": "ARROZ AGULHINHA ARROZAL T1 1KG",
			"gtin": 7896276060045,
			"width": null,
			"height": null,
			"length": null,
			"net_weight": null,
			"gross_weight": null,
			"created_at": "2019-02-04T14:35:24.000-02:00",
			"updated_at": "2022-05-24T11:22:11.000-03:00",
			"release_date": null,
			"price": "R$ 2,99 a R$ 4,95",
			"avg_price": 3.97,
			"max_price": 4.95,
			"min_price": 2.99,
			"gtins": [
				{
					"gtin": 7896276060045,
					"commercial_unit": {
						"type_packaging": "Unidade",
						"quantity_packaging": 1,
						"ballast": null,
						"layer": null
					}
				},
				{
					"gtin": 17896276060042,
					"commercial_unit": {
						"type_packaging": "Caixa",
						"quantity_packaging": 10,
						"ballast": 0,
						"layer": 0
					}
				}
			],
			"origin": "COSMOS",
			"barcode_image": "https://api.cosmos.bluesoft.com.br/products/barcode/6DF13DE0AD00FBF430DAB8C424F591AB.png",
			"ncm": {
				"code": "10063021",
				"description": "Polido ou brunido",
				"full_description": "Cereais -  Arroz -  Arroz semibranqueado ou branqueado, mesmo polido ou brunido - Não parboilizado - Polido ou brunido",
				"ex": null
			}
		}
	],
	"current_page": 1,
	"per_page": 30,
	"total_pages": 1,
	"total_count": 1
}


{
	"products": [
		{
			"description": "AÇÚCAR REFINADO UNIÃO 1KGS",
			"gtin": 7891910000197,
			"thumbnail": "https://cdn-cosmos.bluesoft.com.br/products/7891910000197",
			"width": null,
			"height": null,
			"length": null,
			"net_weight": null,
			"gross_weight": null,
			"created_at": "2014-04-24T11:07:34.000-03:00",
			"updated_at": "2022-05-30T15:30:16.000-03:00",
			"release_date": null,
			"price": "R$ 3,79 a R$ 11,98",
			"avg_price": 7.885,
			"max_price": 11.98,
			"min_price": 3.79,
			"gtins": [
				{
					"gtin": 7891910000197,
					"commercial_unit": {
						"type_packaging": "Unidade",
						"quantity_packaging": 1,
						"ballast": null,
						"layer": null
					}
				},
				{
					"gtin": 7891910000203,
					"commercial_unit": {
						"type_packaging": "Caixa",
						"quantity_packaging": 10,
						"ballast": 11,
						"layer": 10
					}
				}
			],
			"origin": "COSMOS",
			"barcode_image": "https://api.cosmos.bluesoft.com.br/products/barcode/D215D0FAC1ACAEF6B65EE7ED9820DD38.png",
			"brand": {
				"name": "UNIAO",
				"picture": ""
			},
			"gpc": {
				"code": "10000043",
				"description": "Açúcar / Substitutos do Açúcar (Não perecível)"
			},
			"ncm": {
				"code": "17019900",
				"description": "Outros",
				"full_description": "Açúcares e produtos de confeitaria - Açúcares de cana ou de beterraba e sacarose quimicamente pura, no estado sólido. - Outros: - Outros",
				"ex": null
			},
			"cest": {
				"id": 2154,
				"code": "1710300",
				"description": "Outros tipos de açúcar, em embalagens de conteúdo inferior ou igual a 2 kg, exceto as embalagens contendo envelopes individualizados (sachês) de conteúdo inferior ou igual a 10 g",
				"parent_id": 1671
			}
		}
	],
	"current_page": 1,
	"per_page": 30,
	"total_pages": 1,
	"total_count": 1
}